financial_accounts/__init__.py
financial_accounts/business/__init__.py
financial_accounts/business/account_service.py
financial_accounts/business/base_service.py
financial_accounts/business/book_service.py
financial_accounts/business/management_service.py
financial_accounts/business/transaction_service.py
financial_accounts/cli.py
financial_accounts/db/__init__.py
financial_accounts/db/data_access.py
financial_accounts/db/models.py
financial_accounts/db/updated_mixin.py
financial_accounts/version.py
financial_accounts-1.0.0.dist-info/LICENSE
financial_accounts-1.0.0.dist-info/METADATA
financial_accounts-1.0.0.dist-info/WHEEL
financial_accounts-1.0.0.dist-info/entry_points.txt
financial_accounts-1.0.0.dist-info/RECORD
