Metadata-Version: 2.1
Name: financial_accounts
Version: 1.0.0
Summary: A personal finance accounting system.
License: MIT
Author: Edward Bridges
Author-email: github@eqbridges.com
Requires-Python: >=3.13,<4.0
Classifier: License :: OSI Approved :: MIT License
Classifier: Programming Language :: Python :: 3
Classifier: Programming Language :: Python :: 3.13
Requires-Dist: sqlalchemy (>=2.0.36,<3.0.0)
Requires-Dist: tomlkit (>=0.13.2,<0.14.0)
